reqcache/__init__.py
reqcache_py-1.0.0.dist-info/LICENSE
reqcache_py-1.0.0.dist-info/METADATA
reqcache_py-1.0.0.dist-info/WHEEL
reqcache_py-1.0.0.dist-info/top_level.txt
reqcache_py-1.0.0.dist-info/RECORD
