Metadata-Version: 2.1
Name: reqcache-py
Version: 1.0.0
Summary: A TTL-based caching wrapper for Python requests library
Author-email: wangys-kits <wyshdiy@hotmail.com>
License: MIT
Project-URL: Homepage, https://github.com/wangys-kits/reqcache
Project-URL: Repository, https://github.com/wangys-kits/reqcache
Keywords: requests,cache,http,web-scraping,data-collection
Classifier: Development Status :: 3 - Alpha
Classifier: Intended Audience :: Developers
Classifier: License :: OSI Approved :: MIT License
Classifier: Programming Language :: Python :: 3
Classifier: Programming Language :: Python :: 3.7
Classifier: Programming Language :: Python :: 3.8
Classifier: Programming Language :: Python :: 3.9
Classifier: Programming Language :: Python :: 3.10
Classifier: Programming Language :: Python :: 3.11
Classifier: Topic :: Internet :: WWW/HTTP
Classifier: Topic :: Software Development :: Libraries :: Python Modules
Requires-Python: >=3.7
License-File: LICENSE
Requires-Dist: requests (>=2.20.0)
Provides-Extra: dev
Requires-Dist: pytest (>=7.0.0) ; extra == 'dev'
Requires-Dist: pytest-cov (>=4.0.0) ; extra == 'dev'
